Workbook

Sheet Controle de Carros
A1: Controle de Compra e Venda de Carros
A2: Preencha as células amarelas. Detalhe as despesas na aba 'Despesas' e documentos na aba 'Documentos'. Custo final, Lucro, Despesas e Status são calculados automaticamente.
A4: ID | B4: Data da compra | C4: Marca | D4: Modelo | E4: Ano | F4: Placa | G4: Sociedade | H4: Antigo dono | I4: Valor de compra | J4: Despesas (total) | K4: Custo final | L4: Valor FIPE | M4: Data da venda | N4: Novo comprador | O4: Valor de venda | P4: Parcelamento | Q4: Valor da entrada | R4: Nº de parcelas | S4: Valor da parcela | T4: Lucro | U4: Status
A5: 1 | B5: 46268 | C5: Fiat | D5: Toro Endurance 2.0 | E5: 2022 | F5: RTM 9G72 | H5: Uai Veiculos | I5: 74900 | J5: =IF(B5="","",SUMIF(Despesas!$A:$A,A5,Despesas!$F:$F)) -> 10200 | K5: =IF(B5="","",I5+J5) -> 85100 | L5: 101000 | M5: 46289 | N5: Lagoa | O5: 148500 | P5: Parcelado | Q5: 41000 | R5: 43 | S5: 2500 | T5: =IF(O5="","",(O5-I5-J5)) -> 63400 | U5: =IF(B5="","",IF(M5="","Em estoque","Vendido")) -> Vendido
A6: 2 | B6: 46268 | C6: Renault | D6: Sandeiro 1.6 8v | E6: 2014 | F6: EZP6E22 | H6: Uai Veiculos | I6: 16900 | J6: =IF(B6="","",SUMIF(Despesas!$A:$A,A6,Despesas!$F:$F)) -> 1035 | K6: =IF(B6="","",I6+J6) -> 17935 | L6: 32000 | M6: 46290 | N6: Cristina | O6: 44000 | P6: Parcelado | Q6: 14000 | R6: 30 | S6: 1000 | T6: =IF(O6="","",(O6-I6-J6)) -> 26065 | U6: =IF(B6="","",IF(M6="","Em estoque","Vendido")) -> Vendido
A7: 3 | B7: 46273 | C7: Hyundai | D7: HB20 | E7: 2015 | F7: FXL5I69 | H7: Suellin | I7: 33000 | J7: =IF(B7="","",SUMIF(Despesas!$A:$A,A7,Despesas!$F:$F)) -> 7251.84 | K7: =IF(B7="","",I7+J7) -> 40251.84 | L7: 50000 | M7: 46297 | N7: NELSON | O7: 78000 | P7: Parcelado | Q7: 18000 | R7: 40 | S7: 1500 | T7: =IF(O7="","",(O7-I7-J7)) -> 37748.16 | U7: =IF(B7="","",IF(M7="","Em estoque","Vendido")) -> Vendido
A8: 4 | B8: 46283 | C8: BMW | D8: X1 | E8: 2013 | F8: EQN1J10 | H8: Giuseppe Maset | I8: 33500 | J8: =IF(B8="","",SUMIF(Despesas!$A:$A,A8,Despesas!$F:$F)) -> 3252.96 | K8: =IF(B8="","",I8+J8) -> 36752.96 | L8: 74000 | T8: =IF(O8="","",(O8-I8-J8)) | U8: Em estoque
A9: 5 | B9: 46294 | C9: GOL | D9: VW GOL 1.0 PRETO FLEX | E9: 2012 | F9: GTO7G79 | G9: Lagoa | H9: Uai Veículos | I9: 19900 | J9: =IF(B9="","",SUMIF(Despesas!$A:$A,A9,Despesas!$F:$F)) -> 200 | K9: =IF(B9="","",I9+J9) -> 20100 | L9: 28990 | T9: =IF(O9="","",(O9-K9)) | U9: Em estoque
A10: =IF(B10="","",ROW()-4) -> 6 | B10: 46294 | C10: ONIX | D10: Chevrolet Onix Lt 1.0 Prata Flex | E10: 2019 | F10: QQD9C35 | G10: Lagoa | H10: Uai Veículos | I10: 34900 | J10: =IF(B10="","",SUMIF(Despesas!$A:$A,A10,Despesas!$F:$F)) -> 2322 | K10: =IF(B10="","",I10+J10) -> 37222 | L10: 53937 | T10: =IF(O10="","",(O10-K10)) | U10: Em estoque
A11: 7 | B11: 46297 | C11: ASTRA | D11: GM/ASTRA HB 4P ADVANTAGE | E11: 2008 | F11: EBM7E53 | H11: NELSON DE SOUZA SILVA | I11: 18000 | J11: =IF(B11="","",SUMIF(Despesas!$A:$A,A11,Despesas!$F:$F)) -> 0 | K11: =IF(B11="","",I11+J11) -> 18000 | L11: 29900 | M11: 46298 | N11: DIOGENES DE SOUZA ARAUJO | O11: 47000 | P11: Parcelado | Q11: 11000 | R11: 36 | S11: 1000 | T11: =IF(O11="","",(O11-K11)) -> 29000 | U11: =IF(B11="","",IF(M11="","Em estoque","Vendido")) -> Vendido
A12: 8 | B12: 46298 | C12: TWISTER | D12: HONDA/CB 250F TWISTER | E12: 2018 | F12: QIU0B54 | G12: Lagoa | H12: DIOGENES DE SOUZA ARAUJO | I12: 11000 | J12: =IF(B12="","",SUMIF(Despesas!$A:$A,A12,Despesas!$F:$F)) -> 0 | K12: =IF(B12="","",I12+J12) -> 11000 | L12: 16900 | U12: =IF(B12="","",IF(M12="","Em estoque","Vendido")) -> Em estoque
A13: =IF(B13="","",ROW()-4) | J13: =IF(B13="","",SUMIF(Despesas!$A:$A,A13,Despesas!$F:$F)) | K13: =IF(B13="","",I13+J13) | T13: =IF(O13="","",(O13-K52)) | U13: =IF(B13="","",IF(M13="","Em estoque","Vendido"))
A14: =IF(B14="","",ROW()-4) | J14: =IF(B14="","",SUMIF(Despesas!$A:$A,A14,Despesas!$F:$F)) | K14: =IF(B14="","",I14+J14) | T14: =IF(O14="","",(O14-K14)) | U14: =IF(B14="","",IF(M14="","Em estoque","Vendido"))
A15: =IF(B15="","",ROW()-4) | J15: =IF(B15="","",SUMIF(Despesas!$A:$A,A15,Despesas!$F:$F)) | K15: =IF(B15="","",I15+J15) | T15: =IF(O15="","",(O15-K15)) | U15: =IF(B15="","",IF(M15="","Em estoque","Vendido"))
A16: =IF(B16="","",ROW()-4) | J16: =IF(B16="","",SUMIF(Despesas!$A:$A,A16,Despesas!$F:$F)) | K16: =IF(B16="","",I16+J16) | T16: =IF(O16="","",(O16-K16)) | U16: =IF(B16="","",IF(M16="","Em estoque","Vendido"))
A17: =IF(B17="","",ROW()-4) | J17: =IF(B17="","",SUMIF(Despesas!$A:$A,A17,Despesas!$F:$F)) | K17: =IF(B17="","",I17+J17) | T17: =IF(O17="","",(O17-K17)) | U17: =IF(B17="","",IF(M17="","Em estoque","Vendido"))
A18: =IF(B18="","",ROW()-4) | J18: =IF(B18="","",SUMIF(Despesas!$A:$A,A18,Despesas!$F:$F)) | K18: =IF(B18="","",I18+J18) | T18: =IF(O18="","",(O18-K18)) | U18: =IF(B18="","",IF(M18="","Em estoque","Vendido"))
A19: =IF(B19="","",ROW()-4) | J19: =IF(B19="","",SUMIF(Despesas!$A:$A,A19,Despesas!$F:$F)) | K19: =IF(B19="","",I19+J19) | T19: =IF(O19="","",(O19-K19)) | U19: =IF(B19="","",IF(M19="","Em estoque","Vendido"))
A20: =IF(B20="","",ROW()-4) | J20: =IF(B20="","",SUMIF(Despesas!$A:$A,A20,Despesas!$F:$F)) | K20: =IF(B20="","",I20+J20) | T20: =IF(O20="","",(O20-K20)) | U20: =IF(B20="","",IF(M20="","Em estoque","Vendido"))
A21: =IF(B21="","",ROW()-4) | J21: =IF(B21="","",SUMIF(Despesas!$A:$A,A21,Despesas!$F:$F)) | K21: =IF(B21="","",I21+J21) | T21: =IF(O21="","",(O21-K21)) | U21: =IF(B21="","",IF(M21="","Em estoque","Vendido"))
A22: =IF(B22="","",ROW()-4) | J22: =IF(B22="","",SUMIF(Despesas!$A:$A,A22,Despesas!$F:$F)) | K22: =IF(B22="","",I22+J22) | T22: =IF(O22="","",(O22-K22)) | U22: =IF(B22="","",IF(M22="","Em estoque","Vendido"))
A23: =IF(B23="","",ROW()-4) | J23: =IF(B23="","",SUMIF(Despesas!$A:$A,A23,Despesas!$F:$F)) | K23: =IF(B23="","",I23+J23) | T23: =IF(O23="","",(O23-K23)) | U23: =IF(B23="","",IF(M23="","Em estoque","Vendido"))
A24: =IF(B24="","",ROW()-4) | J24: =IF(B24="","",SUMIF(Despesas!$A:$A,A24,Despesas!$F:$F)) | K24: =IF(B24="","",I24+J24) | T24: =IF(O24="","",(O24-K24)) | U24: =IF(B24="","",IF(M24="","Em estoque","Vendido"))
A25: =IF(B25="","",ROW()-4) | J25: =IF(B25="","",SUMIF(Despesas!$A:$A,A25,Despesas!$F:$F)) | K25: =IF(B25="","",I25+J25) | T25: =IF(O25="","",(O25-K25)) | U25: =IF(B25="","",IF(M25="","Em estoque","Vendido"))
... A48: =IF(B48="","",ROW()-4) | J48: =IF(B48="","",SUMIF(Despesas!$A:$A,A48,Despesas!$F:$F)) | K48: =IF(B48="","",I48+J48) | T48: =IF(O48="","",(O48-K48)) | U48: =IF(B48="","",IF(M48="","Em estoque","Vendido"))
K49: =IF(B49="","",I49+J49)
K50: =IF(B50="","",I50+J50)
A51: =IF(B51="","",ROW()-4) | J51: =IF(B51="","",SUMIF(Despesas!$A:$A,A51,Despesas!$F:$F)) | K51: =IF(B51="","",I51+J51) | T51: =IF(O51="","",(O51-K51)) | U51: =IF(B51="","",IF(M51="","Em estoque","Vendido"))
I52: =SUM(I5:I12) -> 242100 | J52: =SUM(J5:J12) -> 24261.8 | K52: =SUM(K5:K12) -> 266361.8 | T52: =SUM(T5:T12) -> 156213.16
A53: Legenda:
A54: Células amarelas = preencher manualmente
A55: ID = gerado automaticamente; use esse número nas abas Despesas e Documentos para vincular ao carro
A56: Despesas (total) = soma automática dos itens lançados na aba Despesas
A57: Custo final = Valor de compra + Despesas (total)
A58: Valor FIPE = preencher manualmente com a tabela FIPE do veículo (referência de mercado)
A59: Lucro = Valor de venda - Custo final

Sheet Despesas
A1: Despesas por Veículo (item a item)
A2: Lance cada despesa em uma linha separada. Use o 'ID do veículo' correspondente da aba Controle de Carros.
A4: ID do veículo | B4: Placa (referência) | C4: Modelo | D4: Data da despesa | E4: Item / Descrição | F4: Valor
A5: 1 | B5: RTM 9G72 | C5: Toro Endurance 2.0 | D5: 46275 | E5: Remap Ney | F5: 2000
A6: 1 | B6: RTM 9G72 | C6: Toro Endurance 2.0 | D6: 46275 | E6: Reservatório agua | F6: 100
A7: 1 | B7: RTM 9G72 | C7: Toro Endurance 2.0 | D7: 46275 | E7: Reparo da bomba de vacuo | F7: 100
A8: 1 | B8: RTM 9G72 | C8: Toro Endurance 2.0 | D8: 46280 | E8: Higienização | F8: 500
A9: 1 | B9: RTM 9G72 | C9: Toro Endurance 2.0 | D9: 46290 | E9: Comissão para Lagoa | F9: 5000
A10: 1 | B10: RTM 9G72 | C10: Toro Endurance 2.0 | D10: 46296 | E10: Bomba de alta | F10: 2500
A11: 2 | B11: EZP 6E22 | C11: Sandeiro 1.6 8v | D11: 46275 | E11: Pçs p retífica do cabeçote | F11: 250
A12: 2 | B12: EZP 6E22 | C12: Sandeiro 1.6 8v | D12: 46275 | E12: Higienização | F12: 500
A13: 2 | B13: EZP 6E22 | C13: Sandeiro 1.6 8v | D13: 46280 | E13: Pneus | F13: 200
A14: 2 | B14: EZP 6E22 | C14: Sandeiro 1.6 8v | D14: 46287 | E14: Cabo de vela | F14: 85
A15: 3 | B15: FXL5I69 | C15: HB20 | D15: 46280 | E15: FUNILARIA JOEL | F15: 1500
A16: 3 | B16: FXL5I69 | C16: HB20 | D16: 46291 | E16: PATRIKA VISTORIA | F16: 220
... A36: 6 | B36: QQD9C35 | C36: ONIX | D36: 46301 | E36: Para-choque Diant/Tras | F36: 633
A61: Legenda:
A62: Células amarelas = preencher manualmente
A63: O total de cada carro aparece automaticamente nas colunas 'Despesas (total)' e 'Custo final' da aba Controle de Carros

Sheet Documentos
A1: Documentos e Fotos por Veículo (Google Drive / OneDrive)
A2: Cole aqui o link do Google Drive ou OneDrive de cada arquivo (foto, contrato, CRLV, nota fiscal etc). Clique no link para abrir.
A4: ID do veículo | B4: Placa (referência) | C4: Modelo | D4: Tipo de documento | E4: Link do arquivo | F4: Data de upload
A5: 1 | B5: RTM 9G72 | C5: Toro Endurance 2.1 | D5: CRLV | E5: https://drive.google.com/file/d/1W1LHjCCUqtgjcn_nkKkGcJwBy6uliQeU/view?usp=drive_link | F5: 46279
A6: 2 | B6: EZP6E22 | C6: Sandeiro 1.6 8v | D6: ATPV | E6: ATPV SANDERO.pdf | F6: 46279
A7: 3 | B7: FXL5I69 | C7: HB20 | D7: Laudo Cautelar | E7: https://drive.google.com/file/d/1EuWfmyyBK2JMQDXojVsm5M0HJX-gCQan/view?usp=drive_linkk | F7: 46291
A8: 3 | B8: FXL5I69 | C8: HB20 | D8: Laudo Transferência | E8: https://drive.google.com/file/d/1vVoZDFbQj7h3oyae4x3ye-jgX2LvBhBv/view?usp=drive_link | F8: 46291
A9: 3 | B9: FXL5I69 | C9: HB20 | D9: CRLV | E9: https://drive.google.com/file/d/1T2G3FYgpwWVhxBbt29dgI-Hy7DUwcWt7/view?usp=drive_link | F9: 46296
A10: 4 | B10: EQN1J10 | C10: X1 | D10: CRLV | E10: https://drive.google.com/file/d/1HGKEV554gyggUrUU-OG16qcOXKPwavQu/view?usp=drive_link | F10: 46282
A11: 7 | B11: EBM7E53 | C11: ASTRA | D11: CRLV | E11: https://drive.google.com/file/d/1NDPPjG-anPYcLCGk_HAXp52tnBf6O_UG/view?usp=drive_link | F11: 46299
A12: 8 | B12: QIU0B54 | C12: TWISTER | D12: CRLV | E12: https://drive.google.com/file/d/1AtxRp-ZtSHiyDiuAWOKBwtAYPN56oLaC/view?usp=drive_link | F12: 46299
A83: Legenda:
A84: Células amarelas = preencher manualmente
A85: Cole o link de compartilhamento do Google Drive ou OneDrive na coluna 'Link do arquivo' (deixe o arquivo com permissão de visualização)
A86: Use o mesmo ID do veículo da aba Controle de Carros para vincular os documentos ao carro certo

Sheet Pagamentos 2026
A1: ID | B1: Modelo | C1: Janeiro | D1: Fevereiro | E1: Abril | F1: Maio | G1: Junho | H1: Julho | I1: Agosto | J1: Setembro | K1: Outubro | L1: Novembro | M1: Dezembro
A2: 1 | B2: Toro Endurance 2.0 | J2: 1/43
A3: 2 | B3: Sandeiro 1.6 8v
A4: 3 | B4: HB20
A5: 4 | B5: X1
A6: 5 | B6: VW GOL 1.0 PRETO FLEX
A7: =IF(B7="","",ROW()-4) -> 3 | B7: Chevrolet Onix Lt 1.0 Prata Flex
A8: 7 | B8: GM/ASTRA HB 4P ADVANTAGE
A9: 8 | B9: HONDA/CB 250F TWISTER

Sheet  Pagamentos 2027
A1: ID | B1: Modelo | C1: Janeiro | D1: Fevereiro | E1: Abril | F1: Maio | G1: Junho | H1: Julho | I1: Agosto | J1: Setembro | K1: Outubro | L1: Novembro | M1: Dezembro
A2: 1 | B2: Toro Endurance 2.0
A3: 2 | B3: Sandeiro 1.6 8v
A4: 3 | B4: HB20
A5: 4 | B5: X1
A6: 5 | B6: VW GOL 1.0 PRETO FLEX
A7: =IF(B7="","",ROW()-4) -> 3 | B7: Chevrolet Onix Lt 1.0 Prata Flex
A8: 7 | B8: GM/ASTRA HB 4P ADVANTAGE
A9: 8 | B9: HONDA/CB 250F TWISTER
